ispw_functions/__init__.py
ispw_functions-0.0.1.dist-info/LICENSE
ispw_functions-0.0.1.dist-info/METADATA
ispw_functions-0.0.1.dist-info/WHEEL
ispw_functions-0.0.1.dist-info/top_level.txt
ispw_functions-0.0.1.dist-info/RECORD
